layabauth/__init__.py
layabauth/_http.py
layabauth/_openapi.py
layabauth/flask.py
layabauth/starlette.py
layabauth/testing.py
layabauth/version.py
layabauth-7.0.0.dist-info/LICENSE
layabauth-7.0.0.dist-info/METADATA
layabauth-7.0.0.dist-info/WHEEL
layabauth-7.0.0.dist-info/top_level.txt
layabauth-7.0.0.dist-info/RECORD
