Metadata-Version: 2.1
Name: layabauth
Version: 7.0.0
Summary: Handle OAuth2 authentication for REST APIs
Home-page: https://colin-b.github.io/layabauth/
Author: Colin Bounouar
Author-email: colin.bounouar.dev@gmail.com
Maintainer: Colin Bounouar
Maintainer-email: colin.bounouar.dev@gmail.com
License: MIT
Download-URL: https://pypi.org/project/layabauth/
Project-URL: GitHub, https://github.com/Colin-b/layabauth
Project-URL: Changelog, https://github.com/Colin-b/layabauth/blob/master/CHANGELOG.md
Project-URL: Issues, https://github.com/Colin-b/layabauth/issues
Keywords: flask,starlette,auth
Platform: Windows
Platform: Linux
Classifier: Development Status :: 5 - Production/Stable
Classifier: Intended Audience :: Developers
Classifier: License :: OSI Approved :: MIT License
Classifier: Natural Language :: English
Classifier: Programming Language :: Python
Classifier: Programming Language :: Python :: 3
Classifier: Programming Language :: Python :: 3.7
Classifier: Programming Language :: Python :: 3.8
Classifier: Programming Language :: Python :: 3.9
Classifier: Programming Language :: Python :: 3.10
Classifier: Programming Language :: Python :: 3.11
Classifier: Topic :: Software Development :: Build Tools
Requires-Python: >=3.7
Requires-Dist: httpx (==0.24.*)
Requires-Dist: python-jose (==3.*)
Provides-Extra: testing
Requires-Dist: flask-restx (==1.1.*) ; extra == 'testing'
Requires-Dist: pytest-flask (==1.*) ; extra == 'testing'
Requires-Dist: starlette (==0.17.*) ; extra == 'testing'
Requires-Dist: requests (==2.*) ; extra == 'testing'
Requires-Dist: pytest-httpx (==0.22.*) ; extra == 'testing'
Requires-Dist: pytest-cov (==3.*) ; extra == 'testing'
